[
    {
        "id": "95573097fedd403fb488d3bcc64cd8df",
        "platform": "AtCoder",
        "title": "UNIQUE VISION Programming Contest 2025 Christmas (AtCoder Beginner Contest 437)",
        "url": "https://atcoder.jp/contests/abc437",
        "start_time": "2025-12-20T17:30:00+05:30",
        "duration": 6000
    },
    {
        "id": "5c9b1125a36244bbba1988aa23149d58",
        "platform": "AtCoder",
        "title": "AtCoder Grand Contest 075",
        "url": "https://atcoder.jp/contests/agc075",
        "start_time": "2025-12-21T17:30:00+05:30",
        "duration": 10800
    },
    {
        "id": "b9d8522d5b974fe1a0b99cf5fef2f51e",
        "platform": "AtCoder",
        "title": "AtCoder Beginner Contest 438",
        "url": "https://atcoder.jp/contests/abc438",
        "start_time": "2025-12-27T17:30:00+05:30",
        "duration": 6000
    },
    {
        "id": "f6a0fe89865e4808a52b40cb65d9cef6",
        "platform": "AtCoder",
        "title": "AtCoder Grand Contest 076",
        "url": "https://atcoder.jp/contests/agc076",
        "start_time": "2025-12-28T17:30:00+05:30",
        "duration": 10800
    },
    {
        "id": "8825a4d042014b3a92aed1805d3b3e86",
        "platform": "AtCoder",
        "title": "AtCoder Beginner Contest 439",
        "url": "https://atcoder.jp/contests/abc439",
        "start_time": "2026-01-03T17:30:00+05:30",
        "duration": 6000
    },
    {
        "id": "d3e8a7c5993048a6a7a3b229c36410df",
        "platform": "AtCoder",
        "title": "AtCoder Beginner Contest 440",
        "url": "https://atcoder.jp/contests/abc440",
        "start_time": "2026-01-10T17:30:00+05:30",
        "duration": 6000
    },
    {
        "id": "6f0ee99108b74755b93a91c5f1bbf420",
        "platform": "AtCoder",
        "title": "AtCoder Regular Contest 212 (Div. 2)",
        "url": "https://atcoder.jp/contests/arc212",
        "start_time": "2026-01-11T17:30:00+05:30",
        "duration": 7200
    },
    {
        "id": "09c4d99c8e9a4239a511392ffa4845c3",
        "platform": "AtCoder",
        "title": "AtCoder Beginner Contest 441 (Promotion of Engineer Guild Fes)",
        "url": "https://atcoder.jp/contests/abc441",
        "start_time": "2026-01-17T17:30:00+05:30",
        "duration": 6000
    },
    {
        "id": "a02a41c490154e8c8df0760a5bcc6653",
        "platform": "Codeforces",
        "title": "Good Bye 2025",
        "url": "https://codeforces.com/contests/2178",
        "start_time": "2025-12-27T20:05:00+05:30",
        "duration": 10800
    },
    {
        "id": "8216a09b05a84f72b85dc990b27520ef",
        "platform": "Codeforces",
        "title": "ICPC 2025 Online Winter Challenge powered by Huawei",
        "url": "https://codeforces.com/contests/2177",
        "start_time": "2025-12-26T16:30:00+05:30",
        "duration": 1382400
    },
    {
        "id": "59be057b03774235b71c4cff1471cba0",
        "platform": "Codeforces",
        "title": "Codeforces Round (Div. 3)",
        "url": "https://codeforces.com/contests/2179",
        "start_time": "2025-12-23T20:05:00+05:30",
        "duration": 9000
    },
    {
        "id": "aa847271a3364e1a9050581042400b54",
        "platform": "Codeforces",
        "title": "Codeforces Global Round 31 (Div. 1 + Div. 2)",
        "url": "https://codeforces.com/contests/2180",
        "start_time": "2025-12-19T20:05:00+05:30",
        "duration": 9000
    },
    {
        "id": "d91375ed662f42c8abe45ded3c69ca5d",
        "platform": "Codeforces",
        "title": "2025-2026 ICPC, NERC, Northern Eurasia Finals (Unrated, Online Mirror, ICPC Rules, Teams Preferred)",
        "url": "https://codeforces.com/contests/2181",
        "start_time": "2025-12-17T13:35:00+05:30",
        "duration": 18000
    },
    {
        "id": "53f099d2f3c3453fab9abe473ecc5af1",
        "platform": "LeetCode",
        "title": "Weekly Contest 481",
        "url": "https://leetcode.com/contest/weekly-contest-481",
        "start_time": "2025-12-21T08:00:00+05:30",
        "duration": 5400
    },
    {
        "id": "d060a33ee608485fa4e93829e8d6a29b",
        "platform": "LeetCode",
        "title": "Biweekly Contest 172",
        "url": "https://leetcode.com/contest/biweekly-contest-172",
        "start_time": "2025-12-20T20:00:00+05:30",
        "duration": 5400
    }
]