[
    {
        "id": "04b174f4af044fb29dbcdc46f7c72783",
        "platform": "AtCoder",
        "title": "The 2nd Masters Championship-qual-",
        "url": "https://atcoder.jp/contests/masters2025-qual",
        "start_time": "2025-03-02T09:30:00+05:30",
        "duration": 21600
    },
    {
        "id": "e38ed01eae1a42068ad114a8fe6a603c",
        "platform": "AtCoder",
        "title": "AtCoder Beginner Contest 396",
        "url": "https://atcoder.jp/contests/abc396",
        "start_time": "2025-03-08T17:30:00+05:30",
        "duration": 6000
    },
    {
        "id": "7182b162fef949a3a81a8a45fd884f8e",
        "platform": "AtCoder",
        "title": "AtCoder Regular Contest 194 (Div. 2)",
        "url": "https://atcoder.jp/contests/arc194",
        "start_time": "2025-03-09T17:30:00+05:30",
        "duration": 7200
    },
    {
        "id": "b88ac73bedde41f4b9ddd4f2689cdb12",
        "platform": "AtCoder",
        "title": "OMRON Corporation Programming Contest 2025 (AtCoder Beginner Contest 397)",
        "url": "https://atcoder.jp/contests/abc397",
        "start_time": "2025-03-15T17:30:00+05:30",
        "duration": 6000
    },
    {
        "id": "e18b05294fde4a67876a824c0c6525b8",
        "platform": "AtCoder",
        "title": "AtCoder Heuristic Contest 044",
        "url": "https://atcoder.jp/contests/ahc044",
        "start_time": "2025-03-16T15:30:00+05:30",
        "duration": 14400
    },
    {
        "id": "8ab5ad3839be4a858974cbd8ee6ce42e",
        "platform": "AtCoder",
        "title": "UNIQUE VISION Programming Contest 2025 Spring (AtCoder Beginner Contest 398)",
        "url": "https://atcoder.jp/contests/abc398",
        "start_time": "2025-03-22T17:30:00+05:30",
        "duration": 6000
    },
    {
        "id": "58cf061eead34865a58002d33cdafe9b",
        "platform": "AtCoder",
        "title": "AtCoder Regular Contest 195 (Div. 2)",
        "url": "https://atcoder.jp/contests/arc195",
        "start_time": "2025-03-23T17:30:00+05:30",
        "duration": 7200
    },
    {
        "id": "b354663f06894cb79a4e66bbab8a5052",
        "platform": "AtCoder",
        "title": "THIRD PROGRAMMING CONTEST 2025(AtCoder Heuristic Contest 045)",
        "url": "https://atcoder.jp/contests/ahc045",
        "start_time": "2025-03-28T15:30:00+05:30",
        "duration": 864000
    },
    {
        "id": "cd6bac16f5e04bc6adf5698d674499d2",
        "platform": "AtCoder",
        "title": "AtCoder Grand Contest 071",
        "url": "https://atcoder.jp/contests/agc071",
        "start_time": "2025-03-30T17:30:00+05:30",
        "duration": 10800
    },
    {
        "id": "a8ec2145e7174d028fa1fe79345dd9e5",
        "platform": "AtCoder",
        "title": "AtCoder Beginner Contest 410",
        "url": "https://atcoder.jp/contests/abc410",
        "start_time": "2025-06-14T17:30:00+05:30",
        "duration": 6000
    },
    {
        "id": "0b995b7b99b4400bbb8b7c6092ab9c63",
        "platform": "AtCoder",
        "title": "World Tour Finals 2025 Algorithm",
        "url": "https://atcoder.jp/contests/awtf2025algo",
        "start_time": "2025-07-17T08:30:00+05:30",
        "duration": 18000
    },
    {
        "id": "12b788a4c532498282a4ace5ae80860c",
        "platform": "AtCoder",
        "title": "World Tour Finals 2025 Algorithm(Open Contest)",
        "url": "https://atcoder.jp/contests/awtf2025algo-open",
        "start_time": "2025-07-17T08:30:00+05:30",
        "duration": 18000
    },
    {
        "id": "59bf2fab8cde407ab778b0fd8cf8c827",
        "platform": "CodeChef",
        "title": "Starters 176",
        "url": "https://www.codechef.com/START176",
        "start_time": "2025-03-05T20:00:00+05:30",
        "duration": 7200
    },
    {
        "id": "e1b24dc1fbf643aa85402fd548bd76e8",
        "platform": "CodeChef",
        "title": "Starters 177",
        "url": "https://www.codechef.com/START177",
        "start_time": "2025-03-12T20:00:00+05:30",
        "duration": 7200
    },
    {
        "id": "7286c572d3aa41fc9a8b49856063c999",
        "platform": "Codeforces",
        "title": "Codeforces Round (Div. 3)",
        "url": "https://codeforces.com/contests/2074",
        "start_time": "2025-03-11T20:05:00+05:30",
        "duration": 8100
    },
    {
        "id": "f81d5ef013ba4b408620a1da31d42e4c",
        "platform": "Codeforces",
        "title": "European Championship 2025 - Online Mirror (Unrated, ICPC Rules, Teams Preferred)",
        "url": "https://codeforces.com/contests/2068",
        "start_time": "2025-03-02T16:05:00+05:30",
        "duration": 18000
    },
    {
        "id": "991ff78ab3f141689b403ee8c30e6c00",
        "platform": "GeeksforGeeks",
        "title": "GfG Weekly - 196 [Rated Contest]",
        "url": "https://practice.geeksforgeeks.org/contest/gfg-weekly-196-rated-contest",
        "start_time": "2025-03-02T19:00:00+05:30",
        "duration": 5400
    },
    {
        "id": "566bcd35121542eaaec9286a82156583",
        "platform": "GeeksforGeeks",
        "title": "GfG Weekly - 197 [Rated Contest]",
        "url": "https://practice.geeksforgeeks.org/contest/gfg-weekly-197-rated-contest",
        "start_time": "2025-03-09T19:00:00+05:30",
        "duration": 5400
    },
    {
        "id": "6e750eda02124b23b139c347abecd6a8",
        "platform": "GeeksforGeeks",
        "title": "Job-A-thon 43  Hiring Challenge",
        "url": "https://practice.geeksforgeeks.org/contest/job-a-thon-43-hiring-challenge",
        "start_time": "2025-03-21T20:00:00+05:30",
        "duration": 7200
    },
    {
        "id": "7946ad3dbd2f446dabefb85db952ffdd",
        "platform": "LeetCode",
        "title": "Biweekly Contest 152",
        "url": "https://leetcode.com/contest/biweekly-contest-152",
        "start_time": "2025-03-15T20:00:00+05:30",
        "duration": 5400
    },
    {
        "id": "5d8e07785c50493ba404b8b981a27f0d",
        "platform": "LeetCode",
        "title": "Weekly Contest 439",
        "url": "https://leetcode.com/contest/weekly-contest-439",
        "start_time": "2025-03-02T08:00:00+05:30",
        "duration": 5400
    }
]