[
    {
        "id": "d0827c4c94f747919dcccfcd99eaec15",
        "platform": "AtCoder",
        "title": "SuntoryProgrammingContest2024\uff08AtCoder Beginner Contest 357\uff09",
        "url": "https://atcoder.jp/contests/abc357",
        "start_time": "2024-06-08T17:30:00+05:30",
        "duration": 6000
    },
    {
        "id": "86f2d80b81ac4207978909d865ac5762",
        "platform": "AtCoder",
        "title": "AtCoder Beginner Contest 358",
        "url": "https://atcoder.jp/contests/abc358",
        "start_time": "2024-06-15T17:30:00+05:30",
        "duration": 6000
    },
    {
        "id": "5c31c1f287f7496ab08ff9858d2ff99d",
        "platform": "AtCoder",
        "title": "Toyota Programming Contest 2024#6\uff08AtCoder Heuristic Contest 034\uff09",
        "url": "https://atcoder.jp/contests/ahc034",
        "start_time": "2024-06-16T11:30:00+05:30",
        "duration": 14400
    },
    {
        "id": "dfb4654c9a884edcb346ccca9781882f",
        "platform": "AtCoder",
        "title": "AtCoder Regular Contest 180",
        "url": "https://atcoder.jp/contests/arc180",
        "start_time": "2024-06-29T17:30:00+05:30",
        "duration": 7200
    },
    {
        "id": "f866b9f760ac4fbfa6b775d85f3ceaa7",
        "platform": "AtCoder",
        "title": "AtCoder Beginner Contest 360",
        "url": "https://atcoder.jp/contests/abc360",
        "start_time": "2024-06-30T17:30:00+05:30",
        "duration": 6000
    },
    {
        "id": "1ecdbb887353433482d80cd2cf5f6c7e",
        "platform": "AtCoder",
        "title": "Denso Create Programming Contest 2024\uff08AtCoder Beginner Contest 361\uff09",
        "url": "https://atcoder.jp/contests/abc361",
        "start_time": "2024-07-06T17:30:00+05:30",
        "duration": 6000
    },
    {
        "id": "f4b38dca2cf94cfe976e6a7bd630cce5",
        "platform": "CodeChef",
        "title": "Starters 137",
        "url": "https://www.codechef.com/START137",
        "start_time": "2024-06-05T20:00:00+05:30",
        "duration": 7200
    },
    {
        "id": "6387a671562b4d528812e42f9d9d2844",
        "platform": "CodeChef",
        "title": "Starters 138",
        "url": "https://www.codechef.com/START138",
        "start_time": "2024-06-12T20:00:00+05:30",
        "duration": 7200
    },
    {
        "id": "6c0041a1da0a4ae48f3f1968a79670f3",
        "platform": "Codeforces",
        "title": "Codeforces Round (Div. 2)",
        "url": "https://codeforces.com/contests/1983",
        "start_time": "2024-07-07T20:05:00+05:30",
        "duration": 7200
    },
    {
        "id": "05b1b6d935b34726b6f2fcc56a02d459",
        "platform": "Codeforces",
        "title": "Codeforces Round (Div. 2)",
        "url": "https://codeforces.com/contests/1978",
        "start_time": "2024-06-16T14:35:00+05:30",
        "duration": 7200
    },
    {
        "id": "41d4f6822f9f4789872640f37019623f",
        "platform": "Codeforces",
        "title": "Codeforces Global Round 26",
        "url": "https://codeforces.com/contests/1984",
        "start_time": "2024-06-09T20:05:00+05:30",
        "duration": 10800
    },
    {
        "id": "5d0a1a3535f646899a0963ebbb90c5f0",
        "platform": "Codeforces",
        "title": "Codeforces Round (Div. 2)",
        "url": "https://codeforces.com/contests/1979",
        "start_time": "2024-06-06T20:05:00+05:30",
        "duration": 7200
    },
    {
        "id": "a00b08fc7c01483089195fb41f2d39d5",
        "platform": "Codeforces",
        "title": "Codeforces Round 950 (Div. 3)",
        "url": "https://codeforces.com/contests/1980",
        "start_time": "2024-06-03T20:05:00+05:30",
        "duration": 8100
    },
    {
        "id": "01aa230a702e47a79ffb9f5463344975",
        "platform": "GeeksforGeeks",
        "title": "GFG Weekly - 158 [Rated Contest]",
        "url": "https://practice.geeksforgeeks.org/contest/gfg-weekly-158-rated-contest",
        "start_time": "2024-06-10T00:30:00+05:30",
        "duration": 5400
    },
    {
        "id": "e4bb62cde583459b944e6ad63942a357",
        "platform": "GeeksforGeeks",
        "title": "Job-A-Thon 34 Hiring Challenge",
        "url": "https://practice.geeksforgeeks.org/contest/job-a-thon-34-hiring-challenge",
        "start_time": "2024-06-22T01:30:00+05:30",
        "duration": 9000
    },
    {
        "id": "c3cd3999f96f4a5f9d5f78febf2c8768",
        "platform": "LeetCode",
        "title": "Weekly Contest 401",
        "url": "https://leetcode.com/contest/weekly-contest-401",
        "start_time": "2024-06-09T08:00:00+05:30",
        "duration": 5400
    },
    {
        "id": "31a8d0285b3b4990a97935342d339b95",
        "platform": "LeetCode",
        "title": "Biweekly Contest 132",
        "url": "https://leetcode.com/contest/biweekly-contest-132",
        "start_time": "2024-06-08T20:00:00+05:30",
        "duration": 5400
    }
]