[
    {
        "id": "a51f09309cc74fd3a4baf1e12214be7d",
        "platform": "AtCoder",
        "title": "AtCoder Beginner Contest 380",
        "url": "https://atcoder.jp/contests/abc380",
        "start_time": "2024-11-16T17:30:00+05:30",
        "duration": 6000
    },
    {
        "id": "f31e85c575eb467db13f8396a190c4f5",
        "platform": "AtCoder",
        "title": "AtCoder Regular Contest 187",
        "url": "https://atcoder.jp/contests/arc187",
        "start_time": "2024-11-17T17:30:00+05:30",
        "duration": 7200
    },
    {
        "id": "770679de381e42c7972f40ec8cc32e45",
        "platform": "AtCoder",
        "title": "AtCoder Beginner Contest 381",
        "url": "https://atcoder.jp/contests/abc381",
        "start_time": "2024-11-22T17:30:00+05:30",
        "duration": 6000
    },
    {
        "id": "a2a7de4b1e9c4561bfd6c82b765f6e0a",
        "platform": "AtCoder",
        "title": "estie Programming Contest 2024 (AtCoder Regular Contest 188)",
        "url": "https://atcoder.jp/contests/arc188",
        "start_time": "2024-11-23T17:30:00+05:30",
        "duration": 7200
    },
    {
        "id": "ee5b5420af574b8a976da9ba1376d275",
        "platform": "AtCoder",
        "title": "AtCoder Grand Contest 069",
        "url": "https://atcoder.jp/contests/agc069",
        "start_time": "2024-11-24T17:30:00+05:30",
        "duration": 10800
    },
    {
        "id": "6a1cb0420daf432b9f7cf716be225e7d",
        "platform": "AtCoder",
        "title": "HACK TO THE FUTURE 2025  (AtCoder Heuristic Contest 040)",
        "url": "https://atcoder.jp/contests/ahc040",
        "start_time": "2024-11-29T15:30:00+05:30",
        "duration": 864000
    },
    {
        "id": "8b2c89c317764f57a03c0f18ffb9145c",
        "platform": "AtCoder",
        "title": "AtCoder Beginner Contest 382",
        "url": "https://atcoder.jp/contests/abc382",
        "start_time": "2024-11-30T17:30:00+05:30",
        "duration": 6000
    },
    {
        "id": "317d5a64e2024fed8e255ff9143d3250",
        "platform": "AtCoder",
        "title": "Daiwa Securities Co. Ltd. Programming Contest 2024(AtCoder Beginner Contest 383)",
        "url": "https://atcoder.jp/contests/abc383",
        "start_time": "2024-12-07T17:30:00+05:30",
        "duration": 6000
    },
    {
        "id": "d10a70bc023b4649b7b9780b1dad16da",
        "platform": "AtCoder",
        "title": "Toyota Programming Contest 2024#12(AtCoder Beginner Contest 384)",
        "url": "https://atcoder.jp/contests/abc384",
        "start_time": "2024-12-14T17:30:00+05:30",
        "duration": 6000
    },
    {
        "id": "fd7221e76b94458895b01e4e4e2505f8",
        "platform": "AtCoder",
        "title": "AtCoder Grand Contest 070",
        "url": "https://atcoder.jp/contests/agc070",
        "start_time": "2024-12-29T17:30:00+05:30",
        "duration": 10800
    },
    {
        "id": "8922f3b555b14266b31582a4fb5f9d9d",
        "platform": "AtCoder",
        "title": "The 2nd Masters Championship-qual-",
        "url": "https://atcoder.jp/contests/masters2025-qual",
        "start_time": "2025-03-02T09:30:00+05:30",
        "duration": 21600
    },
    {
        "id": "2f88980418444928bec674d672d54a88",
        "platform": "CodeChef",
        "title": "Starters 161",
        "url": "https://www.codechef.com/START161",
        "start_time": "2024-11-20T20:00:00+05:30",
        "duration": 7200
    },
    {
        "id": "c202c6602ca048d08f0301550dbfb6fc",
        "platform": "CodeChef",
        "title": "Starters 162",
        "url": "https://www.codechef.com/START162",
        "start_time": "2024-11-27T20:00:00+05:30",
        "duration": 7200
    },
    {
        "id": "75e8fd604963488db01c6bf670335527",
        "platform": "Codeforces",
        "title": "Rayan Programming Contest 2024 - Selection (Codeforces Round, Div. 1 + Div. 2)",
        "url": "https://codeforces.com/contests/2034",
        "start_time": "2024-11-30T20:05:00+05:30",
        "duration": 7200
    },
    {
        "id": "e9d0b7f0230f40cba8828dedbb308f9a",
        "platform": "Codeforces",
        "title": "CodeTON Round 9 (Div. 1 + Div. 2, Rated, Prizes!)",
        "url": "https://codeforces.com/contests/2039",
        "start_time": "2024-11-23T20:05:00+05:30",
        "duration": 7200
    },
    {
        "id": "bbd4ba83addf4a3baa11966130ab2b71",
        "platform": "Codeforces",
        "title": "2024-2025 ICPC, NERC, Southern and Volga Russian Regional Contest (Unrated, Online Mirror, ICPC Rules, Preferably Teams)",
        "url": "https://codeforces.com/contests/2038",
        "start_time": "2024-11-18T16:05:00+05:30",
        "duration": 18000
    },
    {
        "id": "cb80460888434849bf4d04a520b43c3b",
        "platform": "Codeforces",
        "title": "Codeforces Round (Div. 3)",
        "url": "https://codeforces.com/contests/2037",
        "start_time": "2024-11-17T20:05:00+05:30",
        "duration": 8100
    },
    {
        "id": "d5d7012210c04c069ffe9e9ac5af994c",
        "platform": "Codeforces",
        "title": "Codeforces Round 987 (Div. 2)",
        "url": "https://codeforces.com/contests/2031",
        "start_time": "2024-11-15T18:05:00+05:30",
        "duration": 7200
    },
    {
        "id": "669b5cfed33c46d0bed243f5eb912402",
        "platform": "GeeksforGeeks",
        "title": "GfG Weekly - 181 [Rated Contest]",
        "url": "https://practice.geeksforgeeks.org/contest/gfg-weekly-181-rated-contest",
        "start_time": "2024-11-17T19:00:00+05:30",
        "duration": 5400
    },
    {
        "id": "8b2c8a591486485baafdf774aca7ad3b",
        "platform": "GeeksforGeeks",
        "title": "Job-A-Thon 39 Hiring Challenge",
        "url": "https://practice.geeksforgeeks.org/contest/job-a-thon-39-hiring-challenge",
        "start_time": "2024-11-21T20:00:00+05:30",
        "duration": 9000
    },
    {
        "id": "e94df30b5ade4d5eb6d986fad6b3e4ae",
        "platform": "GeeksforGeeks",
        "title": "GfG Weekly - 182 [Rated Contest]",
        "url": "https://practice.geeksforgeeks.org/contest/gfg-weekly-182-rated-contest",
        "start_time": "2024-11-24T19:00:00+05:30",
        "duration": 5400
    },
    {
        "id": "4bc6227a8bf24a07b79c750e40b93591",
        "platform": "LeetCode",
        "title": "Biweekly Contest 144",
        "url": "https://leetcode.com/contest/biweekly-contest-144",
        "start_time": "2024-11-23T20:00:00+05:30",
        "duration": 5400
    },
    {
        "id": "6337ede8f44740b4b730ee37bd657549",
        "platform": "LeetCode",
        "title": "Weekly Contest 424",
        "url": "https://leetcode.com/contest/weekly-contest-424",
        "start_time": "2024-11-17T08:00:00+05:30",
        "duration": 5400
    }
]