[
    {
        "id": "08a6018dcddd4f659af371d052533cff",
        "platform": "AtCoder",
        "title": "AtCoder Heuristic Contest 050",
        "url": "https://atcoder.jp/contests/ahc050",
        "start_time": "2025-07-06T15:30:00+05:30",
        "duration": 14400
    },
    {
        "id": "00dac47c63bc43bcbd80b538f9e82e20",
        "platform": "AtCoder",
        "title": " Mirrativ Programming Contest 2025 (AtCoder Beginner Contest 414)",
        "url": "https://atcoder.jp/contests/abc414",
        "start_time": "2025-07-12T17:30:00+05:30",
        "duration": 6000
    },
    {
        "id": "f14a92bcd5ba4e9f8f2c13f150009082",
        "platform": "AtCoder",
        "title": "World Tour Finals 2025 Heuristic",
        "url": "https://atcoder.jp/contests/awtf2025heuristic",
        "start_time": "2025-07-16T05:30:00+05:30",
        "duration": 36000
    },
    {
        "id": "d9b393bda2e640d1ac4e580e88ee4507",
        "platform": "AtCoder",
        "title": "World Tour Finals 2025 Algorithm",
        "url": "https://atcoder.jp/contests/awtf2025algo",
        "start_time": "2025-07-17T08:30:00+05:30",
        "duration": 18000
    },
    {
        "id": "3f2da3813f924dbe89294d0c207753d2",
        "platform": "AtCoder",
        "title": "World Tour Finals 2025 Algorithm(Open Contest)",
        "url": "https://atcoder.jp/contests/awtf2025algo-open",
        "start_time": "2025-07-17T08:30:00+05:30",
        "duration": 18000
    },
    {
        "id": "bc0bb370bf8c4e0f8fe8f35fdcd9ba0a",
        "platform": "AtCoder",
        "title": "Japan Registry Services (JPRS) Programming Contest 2025#2 (AtCoder Beginner Contest 415)",
        "url": "https://atcoder.jp/contests/abc415",
        "start_time": "2025-07-19T17:30:00+05:30",
        "duration": 6000
    },
    {
        "id": "906fc54bee1144a0925ebbfa7a71f1a6",
        "platform": "AtCoder",
        "title": "AtCoder Regular Contest 202 (Div. 1)",
        "url": "https://atcoder.jp/contests/arc202",
        "start_time": "2025-07-20T17:30:00+05:30",
        "duration": 9000
    },
    {
        "id": "cded360c44684c6cb29ff54d20417b30",
        "platform": "AtCoder",
        "title": "THIRD Programming Contest 2025 Summer(AtCoder Heuristic Contest 051)",
        "url": "https://atcoder.jp/contests/ahc051",
        "start_time": "2025-08-01T15:30:00+05:30",
        "duration": 864000
    },
    {
        "id": "d3e97170b30a4a4c991f477081a631bb",
        "platform": "AtCoder",
        "title": "AtCoder Beginner Contest 419",
        "url": "https://atcoder.jp/contests/abc419",
        "start_time": "2025-08-16T17:30:00+05:30",
        "duration": 6000
    },
    {
        "id": "906b13b1e03b4f099ab09deca338dc8b",
        "platform": "CodeChef",
        "title": "Starters 194",
        "url": "https://www.codechef.com/START194",
        "start_time": "2025-07-09T20:00:00+05:30",
        "duration": 7200
    },
    {
        "id": "c9f28e8eabaf4c78b0f68216e9334337",
        "platform": "CodeChef",
        "title": "Starters 195",
        "url": "https://www.codechef.com/START195",
        "start_time": "2025-07-16T20:00:00+05:30",
        "duration": 7200
    },
    {
        "id": "b63c189a6fac43a9a95db3d49f60d285",
        "platform": "Codeforces",
        "title": "Codeforces Round (Div. 1 + Div. 2)",
        "url": "https://codeforces.com/contests/2122",
        "start_time": "2025-07-19T20:05:00+05:30",
        "duration": 9000
    },
    {
        "id": "cf1bbbebbb6b4b34a49a2a44564dfd74",
        "platform": "Codeforces",
        "title": "EPIC Institute of Technology Round Summer 2025 (Codeforces Round 1036, Div. 1 + Div. 2)",
        "url": "https://codeforces.com/contests/2124",
        "start_time": "2025-07-06T20:05:00+05:30",
        "duration": 10800
    },
    {
        "id": "6d37bdde2ca6470893fe512c8273fbc5",
        "platform": "GeeksforGeeks",
        "title": "Job-A-thon 46 Hiring Challenge",
        "url": "https://practice.geeksforgeeks.org/contest/job-a-thon-46-hiring-challenge",
        "start_time": "2025-08-21T20:00:00+05:30",
        "duration": 9000
    },
    {
        "id": "b6889f96d0a64f849131453a41713238",
        "platform": "LeetCode",
        "title": "Weekly Contest 459",
        "url": "https://leetcode.com/contest/weekly-contest-459",
        "start_time": "2025-07-20T08:00:00+05:30",
        "duration": 5400
    },
    {
        "id": "49bca37d831f4039b199dfab3aeae25e",
        "platform": "LeetCode",
        "title": "Biweekly Contest 161",
        "url": "https://leetcode.com/contest/biweekly-contest-161",
        "start_time": "2025-07-19T20:00:00+05:30",
        "duration": 5400
    },
    {
        "id": "f323a79fe82e4bf6a3f051d3b1453320",
        "platform": "LeetCode",
        "title": "Weekly Contest 458",
        "url": "https://leetcode.com/contest/weekly-contest-458",
        "start_time": "2025-07-13T08:00:00+05:30",
        "duration": 5400
    }
]